EmbeddedProto/EmbeddedProto.py
EmbeddedProto/Field.py
EmbeddedProto/Oneof.py
EmbeddedProto/ProtoFile.py
EmbeddedProto/TypeDefinitions.py
EmbeddedProto/__init__.py
EmbeddedProto/__main__.py
EmbeddedProto/embedded_proto_options_pb2.py
EmbeddedProto/main.py
EmbeddedProto/version.json
EmbeddedProto/templates/FieldBasic_Deserialize.h.jinja2
EmbeddedProto/templates/FieldBasic_GetSet.h.jinja2
EmbeddedProto/templates/FieldBasic_Serialize.h.jinja2
EmbeddedProto/templates/FieldBytes_GetSet.h.jinja2
EmbeddedProto/templates/FieldEnum_Deserialize.h.jinja2
EmbeddedProto/templates/FieldEnum_GetSet.h.jinja2
EmbeddedProto/templates/FieldEnum_Serialize.h.jinja2
EmbeddedProto/templates/FieldErrorRecursive_GetSet.h.jinja2
EmbeddedProto/templates/FieldMsg_Deserialize.h.jinja2
EmbeddedProto/templates/FieldMsg_GetSet.h.jinja2
EmbeddedProto/templates/FieldMsg_Serialize.h.jinja2
EmbeddedProto/templates/FieldRepeated_GetSet.h.jinja2
EmbeddedProto/templates/FieldRepeated_Serialize.h.jinja2
EmbeddedProto/templates/FieldStringBytes_Serialize.h.jinja2
EmbeddedProto/templates/FieldString_GetSet.h.jinja2
EmbeddedProto/templates/Header.h.jinja2
EmbeddedProto/templates/TypeDefEnum.h.jinja2
EmbeddedProto/templates/TypeDefMsg.h.jinja2
EmbeddedProto/templates/TypeOneof.h.jinja2
EmbeddedProto-4.0.0.dev20.dist-info/METADATA
EmbeddedProto-4.0.0.dev20.dist-info/WHEEL
EmbeddedProto-4.0.0.dev20.dist-info/entry_points.txt
EmbeddedProto-4.0.0.dev20.dist-info/top_level.txt
EmbeddedProto-4.0.0.dev20.dist-info/RECORD
