Metadata-Version: 2.1
Name: EmbeddedProto
Version: 4.0.0.dev20
Summary: EmbeddedProto generator
Author-email: "Embedded AMS B.V." <info@EmbeddedAMS.nl>
License: GPL-3.0 for Open Source projects, a Property license for Commercial companies.
Requires-Python: >=3.8
Requires-Dist: Jinja2 <4,>=3
Requires-Dist: MarkupSafe <3,>=2.0
Requires-Dist: six <2,>=1.16.0
Requires-Dist: toposort <2,>=1.7
Requires-Dist: protobuf ==5.27.2
Requires-Dist: grpcio-tools ==1.66.0
